{"suppliers":[{"name":"Поставщик 1","address":"Москва, ул. Примерная, 10","phone":"+7 123 456 7890","bank":"Банк 1","accountNumber":"1234567890123456","inn":"1234567890"},{"name":"Поставщик 2","address":"Хабаровск, ул. Воинская, 40","phone":"+7 666 777 2288","bank":"Банк 2","accountNumber":"0987654321123456","inn":"0987654321"},{"name":"Поставщик 3","address":"Искитим, ул. Железная, 87","phone":"+7 913 408 9040","bank":"Банк 3","accountNumber":"8346129567409376","inn":"7659846570"},{"name":"Поставщик 4","address":"Красноярск, ул. Забытая, 5","phone":"+7 999 500 9070","bank":"Банк 4","accountNumber":"5409675987451234","inn":"67409865784"},{"name":"макс","address":"ррмывацу","phone":"55555555555","bank":"513263745","accountNumber":"523656727","inn":"4274567243561"},{"name":"пкувп","address":"пуцып","phone":"цпкып","bank":"ып","accountNumber":"уцыпы","inn":"укпы"},{"name":"Макс","address":"москва","phone":"44444444444","bank":"413256","accountNumber":"23451543765374362","inn":"13423645732"},{"name":"fvrewsvs","address":"vdsv","phone":"vvd","bank":"svsdv","accountNumber":"vsd","inn":"svsdd"},{"name":"svd","address":"vsvd","phone":"sdv","bank":"sdv","accountNumber":"sdv","inn":"svd"},{"name":"сфы","address":"сф","phone":"ыс","bank":"фсы","accountNumber":"сф","inn":"сфы"},{"name":"мквм","address":"ымцу","phone":"мкы","bank":"вм","accountNumber":"йцум","inn":"ывам"},{"name":"мыум","address":"кумц","phone":"мвы","bank":"мцу","accountNumber":"мкы","inn":"вм4234532145312"},{"name":"vesv","address":"es","phone":"vesvs","bank":"evs","accountNumber":"v","inn":"esv"},{"name":"vrsev","address":"serv","phone":"srev","bank":"sev","accountNumber":"ersvr","inn":"sve"},{"name":"cesac","address":"aec","phone":"awe","bank":"cea","accountNumber":"","inn":"ce232222"},{"name":"ev","address":"sve","phone":"vsea","bank":"v","accountNumber":"","inn":""},{"name":"муцм","address":"цум","phone":"цум","bank":"цум","accountNumber":"цу","inn":"4214124"}]}